cloudscraper25/__init__.py
cloudscraper25/cloudflare.py
cloudscraper25/cloudflare_v2.py
cloudscraper25/cloudflare_v3.py
cloudscraper25/exceptions.py
cloudscraper25/help.py
cloudscraper25/proxy_manager.py
cloudscraper25/stealth.py
cloudscraper25/turnstile.py
cloudscraper25/captcha/2captcha.py
cloudscraper25/captcha/9kw.py
cloudscraper25/captcha/__init__.py
cloudscraper25/captcha/anticaptcha.py
cloudscraper25/captcha/capmonster.py
cloudscraper25/captcha/capsolver.py
cloudscraper25/captcha/deathbycaptcha.py
cloudscraper25/interpreters/__init__.py
cloudscraper25/interpreters/chakracore.py
cloudscraper25/interpreters/encapsulated.py
cloudscraper25/interpreters/js2py.py
cloudscraper25/interpreters/js2py_interpreter.py
cloudscraper25/interpreters/jsunfuck.py
cloudscraper25/interpreters/native.py
cloudscraper25/interpreters/nodejs.py
cloudscraper25/interpreters/v8.py
cloudscraper25/user_agent/__init__.py
cloudscraper25/user_agent/browsers.json
cloudscraper25-2.7.0.dist-info/licenses/LICENSE
cloudscraper25-2.7.0.dist-info/METADATA
cloudscraper25-2.7.0.dist-info/WHEEL
cloudscraper25-2.7.0.dist-info/top_level.txt
cloudscraper25-2.7.0.dist-info/RECORD
