Metadata-Version: 2.4
Name: cloudscraper25
Version: 2.7.0
Summary: Enhanced Python module to bypass Cloudflare's anti-bot page with support for v2 challenges, proxy rotation, and stealth mode.
Home-page: https://github.com/zinzied/cloudscraper25
Author: Zied Boughdir, VeNoMouS
Author-email: ziedboughdir@gmail.com
Keywords: cloudflare,scraping,ddos,scrape,webscraper,anti-bot,waf,iuam,bypass,challenge
Classifier: Development Status :: 5 - Production/Stable
Classifier: Intended Audience :: Developers
Classifier: Natural Language :: English
Classifier: License :: OSI Approved :: MIT License
Classifier: Operating System :: OS Independent
Classifier: Programming Language :: Python
Classifier: Programming Language :: Python :: 3
Classifier: Programming Language :: Python :: 3.6
Classifier: Programming Language :: Python :: 3.7
Classifier: Programming Language :: Python :: 3.8
Classifier: Programming Language :: Python :: 3.9
Classifier: Topic :: Internet :: WWW/HTTP
Classifier: Topic :: Software Development :: Libraries :: Application Frameworks
Classifier: Topic :: Software Development :: Libraries :: Python Modules
License-File: LICENSE
Requires-Dist: requests>=2.9.2
Requires-Dist: requests_toolbelt>=0.9.1
Requires-Dist: pyparsing>=2.4.7
Requires-Dist: pyOpenSSL>=22.0.0
Requires-Dist: pycryptodome>=3.15.0
Requires-Dist: websocket-client>=1.3.3
Requires-Dist: js2py>=0.74
Dynamic: author
Dynamic: author-email
Dynamic: classifier
Dynamic: description
Dynamic: description-content-type
Dynamic: home-page
Dynamic: keywords
Dynamic: license-file
Dynamic: requires-dist
Dynamic: summary
